armor_crypto_mcp/__init__.py
armor_crypto_mcp/armor_client.py
armor_crypto_mcp/armor_mcp.py
armor_crypto_mcp-0.2.1.dist-info/METADATA
armor_crypto_mcp-0.2.1.dist-info/WHEEL
armor_crypto_mcp-0.2.1.dist-info/entry_points.txt
armor_crypto_mcp-0.2.1.dist-info/licenses/LICENSE
armor_crypto_mcp-0.2.1.dist-info/RECORD
