Metadata-Version: 2.4
Name: armor-crypto-mcp
Version: 0.2.1
Summary: MCP to interface with multiple blockchains, staking, DeFi, swap, bridging, wallet management, DCA, Limit Orders, Coin Lookup, Tracking and more
Author-email: Armor Wallet <info@armorwallet.ai>
License-File: LICENSE
Requires-Python: >=3.11
Requires-Dist: httpx
Requires-Dist: mcp>=1.1.0
Requires-Dist: python-dotenv>=1.0.0
Requires-Dist: requests>=2.31.0
Requires-Dist: uvicorn>=0.32.1
